asr
asr_cat
asr_deepspeech
